<?xml version="1.0" encoding="utf-8"?>
<modification>
    <name>MultiSafepay: Patch for OnePage Checkout 4.0.0 for OC version 2.3.X</name>
    <version>1.0</version>
    <code>MSP-ONEPAGE-CHECKOUT-BY-EXTENSIONS-BAZAAR-PATCH</code>
    <author>MultiSafepay</author>
    <link>https://www.multisafepay.com</link>
    <file path="admin/controller/checkout/onepagecheckout.php">
        <operation info="Operation 1">
            <search><![CDATA[$this->tpl = (defined('VERSION') && version_compare(VERSION,'2.2.0.0','>=')) ? false : '.tpl';]]></search>
            <add position="after"><![CDATA[
		 $this->registry->set('multisafepay', new Multisafepay($registry));
            ]]>
            </add>
        </operation>
        <operation info="Operation 2">
            <search><![CDATA[$data['payment_methods'][] = array(]]></search>
            <add position="after" offset="6"><![CDATA[
        $multisafepay_methods = $this->multisafepay->getGateways();
        $multisafepay_payments_for_onepagecheckout = array();
        foreach ($multisafepay_methods as $multisafepay_method) {
            $multisafepay_payments_for_onepagecheckout[] = array(
                'title' 		=> $multisafepay_method['description'],
                'code'			=> $multisafepay_method['route'],
                'thumb'			=> $this->model_tool_image->resize('no_image.png', 100, 100),
            );
        }
        $data['payment_methods'] = $this->array_multidimensional_unique(array_merge($data['payment_methods'], $multisafepay_payments_for_onepagecheckout));
            ]]>
            </add>
        </operation>
        <operation info="Operation 3">
            <search><![CDATA[public function index() {]]></search>
            <add position="before"><![CDATA[
        public function array_multidimensional_unique($input){
            $output = array_map("unserialize",
            array_unique(array_map("serialize", $input)));
            return $output;
        }
            ]]>
            </add>
        </operation>
    </file>
    <file path="catalog/controller/onepagecheckout/payment_method.php">
        <operation info="Operation 1">
            <search><![CDATA[public function savepayment(){]]></search>
            <add position="before"><![CDATA[
    private function sortMethods($method_data) {
		$sort_order = array();
		foreach($method_data as $key => $value) {
			if(strpos($key, 'multisafepay') !== false && $value['sort_order']) {
				$sort_order[$key] = $this->config->get('payment_multisafepay_sort_order') . '.' . $value['sort_order'];
			}
			if(strpos($key, 'multisafepay') !== false && !$value['sort_order']) {
				$sort_order[$key] = $this->config->get('payment_multisafepay_sort_order');
			}
			if(strpos($key, 'multisafepay') === false) {
				$sort_order[$key] = $value['sort_order'];
			}
		}
		array_multisort($sort_order, SORT_ASC, SORT_NATURAL, $method_data);
		return $method_data;
	}

	private function extractPaymentMethodsArray($method, $extension, $total, $recurring = false, $method_data = array()) {
		if ($method && $extension['code'] === 'multisafepay') {
			$methods = $this->{'model_extension_payment_'.$extension['code']}->getMethods($this->session->data['payment_address'],
				$total);
			foreach ($methods as $msp_method) {
				$method_data[$msp_method['code']] = $msp_method;
			}
			return $method_data;
		}
		if ($method && $extension['code'] !== 'multisafepay' && $recurring) {
			if (property_exists($this->{'model_extension_payment_'.$extension['code']},
					'recurringPayments') && $this->{'model_extension_payment_'.$extension['code']}->recurringPayments()) {
				$method_data[$method['code']] = $method;
				return $method_data;
			}
		}
		if ($method && $extension['code'] !== 'multisafepay' && !$recurring) {
			$method_data[$method['code']] = $method;
			return $method_data;
		}
	}

	private function getMultiSafepayImageByGatewayRoute($route) {
		$gateways = $this->multisafepay->getGateways();
		$gateway_key = array_search($route, array_column($gateways, 'route'));
		if(isset($gateways[$gateway_key]['image'])) {
			return $gateways[$gateway_key]['image'];
		}
		return false;
	}

	public function __construct($registry) {
		parent::__construct($registry);
		$this->registry->set('multisafepay', new Multisafepay($registry));
		$this->registry->set('multisafepay_version_control', new Multisafepayversioncontrol($registry));
		$this->key_prefix = $this->multisafepay_version_control->getKeyPrefix();
	}
            ]]>
            </add>
        </operation>
        <operation info="Operation 2">
            <search><![CDATA[$recurring = $this->cart->hasRecurringProducts();]]></search>
            <add position="replace" offset="28"><![CDATA[

            $recurring = $this->cart->hasRecurringProducts();

            foreach ($results as $result) {
                if ($this->config->get($this->key_prefix . $result['code'] . '_status')) {
                    $this->load->model('extension/payment/' . $result['code']);
                    $method = $this->{'model_extension_payment_' . $result['code']}->getMethod($this->session->data['payment_address'], $total);
                    $method_data = $this->extractPaymentMethodsArray($method, $result, $total, $recurring, $method_data);
                }
            }

            ]]>
            </add>
        </operation>
        <operation info="Operation 3">
            <search index="1"><![CDATA[$sort_order = array();]]></search>
            <add position="replace" offset="6"><![CDATA[
        $method_data = $this->sortMethods($method_data);
            ]]>
            </add>
        </operation>
    </file>
</modification>